MANIFEST.in
README.md
README.rst
setup.cfg
setup.py
foxtrot/__init__.py
foxtrot/client.py
foxtrot/errors.py
foxtrot/response.py
foxtrot/version.py
foxtrot_client.egg-info/PKG-INFO
foxtrot_client.egg-info/SOURCES.txt
foxtrot_client.egg-info/dependency_links.txt
foxtrot_client.egg-info/requires.txt
foxtrot_client.egg-info/top_level.txt