Metadata-Version: 1.1
Name: foxtrot-client
Version: 0.2.3
Summary: Foxtrot Client Library
Home-page: https://github.com/FoxtrotSystems/api-client-python
Author: Yasyf Mohamedali
Author-email: yasyf@foxtrot.io
License: MIT
Download-URL: https://github.com/FoxtrotSystems/api-client-python/tarball/0.2.3
Keywords: foxtrot,route optimization
Platform: UNKNOWN
Classifier: License :: OSI Approved :: MIT License
Classifier: Development Status :: 4 - Beta
Classifier: Intended Audience :: Developers
Classifier: Programming Language :: Python :: 2
Classifier: Programming Language :: Python :: 2.6
Classifier: Programming Language :: Python :: 2.7
Classifier: Programming Language :: Python :: 3
Classifier: Programming Language :: Python :: 3.2
Classifier: Programming Language :: Python :: 3.3
Classifier: Programming Language :: Python :: 3.4
